{
  "heading": "Output",
  "headingLevel": 2,
  "body": "The command prints the following output if it succeeds.\n\n```json\n{\n  \"ok\": 1,\n  \"cursor\": {\n    \"firstBatch\": [\n      {\n        \"name\": \"<store-name>\",\n        \"provider\": \"s3\",\n        \"region\": \"<region-name>\",\n        \"bucket\": \"<bucket-name>\",\n        \"delimiter\": \"<delimiter>\",\n        \"prefix\": \"<prefix>\"\n      },\n      {\n        \"name\": \"<store-name>\",\n        \"provider\": \"atlas\",\n        \"clusterName\": \"<cluster-name>\",\n        \"projectId\": \"<project-id>\"\n      },\n      ...\n    ],\n    \"id\": NumberLong(0),\n    \"ns\": \"<database>.$cmd.listStores\"\n  }\n}\n```",
  "codeBlocks": [
    {
      "language": "json",
      "content": "{\n  \"ok\": 1,\n  \"cursor\": {\n    \"firstBatch\": [\n      {\n        \"name\": \"<store-name>\",\n        \"provider\": \"s3\",\n        \"region\": \"<region-name>\",\n        \"bucket\": \"<bucket-name>\",\n        \"delimiter\": \"<delimiter>\",\n        \"prefix\": \"<prefix>\"\n      },\n      {\n        \"name\": \"<store-name>\",\n        \"provider\": \"atlas\",\n        \"clusterName\": \"<cluster-name>\",\n        \"projectId\": \"<project-id>\"\n      },\n      ...\n    ],\n    \"id\": NumberLong(0),\n    \"ns\": \"<database>.$cmd.listStores\"\n  }\n}",
      "tokenEstimate": 134
    }
  ]
}
