{
  "heading": "collection.bulkWrite()",
  "headingLevel": 2,
  "body": "Runs multiple insert, update, and delete operations on a collection with\na single call. Within the `bulkWrite()` function, you can specify one\nor more of the following write operations:\n\n- insertOne\n\n- updateOne\n\n- updateMany\n\n- deleteOne\n\n- deleteMany\n\n- replaceOne\n\n> **Note:** A bulk write can only operate on a single collection.\n\n```javascript\nexports = async function(arg){\n    const doc1 = { \"name\": \"velvet elvis\", \"quantity\": 20, \"reviews\": [] };\n    const doc2 = { \"name\": \"mock turtleneck\",  \"quantity\": 30, \"reviews\": [] };\n\n    var collection = context.services.get(\"mongodb-atlas\")\n        .db(\"store\")\n        .collection(\"purchases\");\n\n    return await collection.bulkWrite(\n        [{ insertOne: doc1}, { insertOne: doc2}],\n        {ordered:true});\n};\n```",
  "codeBlocks": [
    {
      "language": "javascript",
      "content": "exports = async function(arg){\n    const doc1 = { \"name\": \"velvet elvis\", \"quantity\": 20, \"reviews\": [] };\n    const doc2 = { \"name\": \"mock turtleneck\",  \"quantity\": 30, \"reviews\": [] };\n\n    var collection = context.services.get(\"mongodb-atlas\")\n        .db(\"store\")\n        .collection(\"purchases\");\n\n    return await collection.bulkWrite(\n        [{ insertOne: doc1}, { insertOne: doc2}],\n        {ordered:true});\n};",
      "tokenEstimate": 112
    }
  ]
}
