{
  "heading": "waitQueueTimeoutMS",
  "headingLevel": 3,
  "body": "`MongoClient` supports multiple concurrent requests. For each process,\ncreate a client and reuse it for all operations in a process. This\npractice is more efficient than creating a client for each request.\n\nThe driver does not limit the number of requests that\ncan wait for sockets to become available, and it is the application's\nresponsibility to limit the size of its pool to bound queuing\nduring a load spike. Requests wait for the amount of time specified in\nthe `waitQueueTimeoutMS` option, which defaults to `0` (no limit).\n\nA request that waits more than the length of time defined by\n`waitQueueTimeoutMS` for a socket raises a connection error. Use this\noption if it is more important to bound the duration of operations\nduring a load spike than it is to complete every operation.\n\nThe following code creates a `MongoClient` instance with a maximum wait queue\ntimeout of `10000` milliseconds (10 seconds) by declaring it in the\n`options` object:\n\n```javascript\nconst { MongoClient } = require('mongodb');\n\nconst uri = '<connection-string>';\nconst client = new MongoClient(uri, {\n  waitQueueTimeoutMS: 10000\n});\n```",
  "codeBlocks": [
    {
      "language": "javascript",
      "content": "const { MongoClient } = require('mongodb');\n\nconst uri = '<connection-string>';\nconst client = new MongoClient(uri, {\n  waitQueueTimeoutMS: 10000\n});",
      "tokenEstimate": 35
    }
  ]
}
