{
  "path": "atlas/set-up-gcp-access",
  "product": "atlas",
  "title": "Set Up and Manage Google Cloud Service Account Access",
  "description": "",
  "headings": [
    {
      "text": "Overview",
      "level": 2,
      "tokenEstimate": 66,
      "slug": "overview",
      "variantAgnostic": true
    },
    {
      "text": "Required Access",
      "level": 2,
      "tokenEstimate": 48,
      "slug": "required-access",
      "variantAgnostic": true
    },
    {
      "text": "Prerequisites",
      "level": 2,
      "tokenEstimate": 19,
      "slug": "prerequisites",
      "variantAgnostic": true
    },
    {
      "text": "Set Up Google Cloud Service Account Access",
      "level": 2,
      "tokenEstimate": 28,
      "slug": "set-up-google-cloud-service-account-access",
      "variantAgnostic": true
    },
    {
      "text": "Set Up Google Cloud Service Account Access",
      "level": 2,
      "tokenEstimate": 18,
      "slug": "set-up-google-cloud-service-account-access--ui",
      "children": [
        {
          "text": "Step 1: Configure Google Cloud Service Account access.",
          "level": 3,
          "tokenEstimate": 40,
          "slug": "step-1-configure-google-cloud-service-account-access--ui",
          "variantAgnostic": false,
          "selections": [
            {
              "interface": "ui"
            }
          ]
        },
        {
          "text": "Step 2: Create a Google Cloud Service Account.",
          "level": 3,
          "tokenEstimate": 204,
          "slug": "step-2-create-a-google-cloud-service-account--ui",
          "variantAgnostic": false,
          "selections": [
            {
              "interface": "ui"
            }
          ]
        }
      ],
      "variantAgnostic": false,
      "selections": [
        {
          "interface": "ui"
        }
      ]
    },
    {
      "text": "View Authorized Google Cloud Service Accounts",
      "level": 2,
      "tokenEstimate": 24,
      "slug": "view-authorized-google-cloud-service-accounts",
      "children": [
        {
          "text": "Step 1: View the authorized Google Cloud service accounts.",
          "level": 3,
          "tokenEstimate": 245,
          "slug": "step-1-view-the-authorized-google-cloud-service-accounts--ui",
          "variantAgnostic": false,
          "selections": [
            {
              "interface": "ui"
            }
          ]
        }
      ],
      "variantAgnostic": false,
      "selections": [
        {
          "interface": "ui"
        }
      ]
    },
    {
      "text": "View Authorized Google Cloud Service Account Details",
      "level": 2,
      "tokenEstimate": 24,
      "slug": "view-authorized-google-cloud-service-account-details",
      "children": [
        {
          "text": "Step 1: View the authorized Google Cloud service accounts.",
          "level": 3,
          "tokenEstimate": 27,
          "slug": "step-1-view-the-authorized-google-cloud-service-accounts--ui",
          "variantAgnostic": false,
          "selections": [
            {
              "interface": "ui"
            }
          ]
        },
        {
          "text": "Step 2: Click the ellipsis () for the Service Account and select  from the dropdown.",
          "level": 3,
          "tokenEstimate": 73,
          "slug": "step-2-click-the-ellipsis-for-the-service-account-and-select-from-the-dropdown--ui",
          "variantAgnostic": false,
          "selections": [
            {
              "interface": "ui"
            }
          ]
        },
        {
          "text": "Step 3: Click  to close the window.",
          "level": 3,
          "tokenEstimate": 106,
          "slug": "step-3-click-to-close-the-window--ui",
          "variantAgnostic": false,
          "selections": [
            {
              "interface": "ui"
            }
          ]
        }
      ],
      "variantAgnostic": false,
      "selections": [
        {
          "interface": "ui"
        }
      ]
    },
    {
      "text": "Remove Authorized Google Cloud Service Account",
      "level": 2,
      "tokenEstimate": 34,
      "slug": "remove-authorized-google-cloud-service-account",
      "children": [
        {
          "text": "Step 1: View the authorized Google Cloud service accounts.",
          "level": 3,
          "tokenEstimate": 27,
          "slug": "step-1-view-the-authorized-google-cloud-service-accounts--ui",
          "variantAgnostic": false,
          "selections": [
            {
              "interface": "ui"
            }
          ]
        },
        {
          "text": "Step 2: Click the  for the Service Account that you wish to remove.",
          "level": 3,
          "tokenEstimate": 6,
          "slug": "step-2-click-the-for-the-service-account-that-you-wish-to-remove--ui",
          "variantAgnostic": false,
          "selections": [
            {
              "interface": "ui"
            }
          ]
        },
        {
          "text": "Step 3: Enter the ID of the Service Account that is shown in the window and click  to remove it.",
          "level": 3,
          "tokenEstimate": 129,
          "slug": "step-3-enter-the-id-of-the-service-account-that-is-shown-in-the-window-and-click-to-remove-it--ui",
          "variantAgnostic": false,
          "selections": [
            {
              "interface": "ui"
            }
          ]
        }
      ],
      "variantAgnostic": false,
      "selections": [
        {
          "interface": "ui"
        }
      ]
    }
  ],
  "tokenEstimate": 1118,
  "codeExamples": {
    "total": 0,
    "byLanguage": {}
  },
  "variantAxes": [
    {
      "value": "interface",
      "text": "interface",
      "default": "ui",
      "selections": [
        {
          "value": "ui",
          "text": "ui"
        },
        {
          "value": "api",
          "text": "api"
        }
      ]
    }
  ]
}
