{
  "heading": "Interface Endpoints",
  "headingLevel": 3,
  "body": "To return the Google Cloud private endpoint interface that you specify. using the\nAtlas CLI, run the following command:\n\n```sh\n\natlas privateEndpoints gcp interfaces describe <id> [options]\n\n```\n\nTo learn more about the command syntax and parameters, see the\nAtlas CLI documentation for [atlas privateEndpoints gcp interfaces describe](atlas/cli/current/command/atlas-privateEndpoints-gcp-interfaces-describe).\n\nAtlas UI\n\nClick Dedicated Cluster for a private endpoint\nfor your dedicated Atlas cluster. (default)",
  "codeBlocks": [
    {
      "language": "sh",
      "content": "\natlas privateEndpoints gcp interfaces describe <id> [options]\n",
      "tokenEstimate": 15
    }
  ],
  "slug": "interface-endpoints",
  "variantAgnostic": true
}
