{
  "path": "atlas/review-real-time-metrics",
  "product": "atlas",
  "title": "Review Real-Time Metrics",
  "description": "To view real-time performance metrics for a specific Atlas cluster\nin a project, click on the name of the cluster\nto open the Cluster sidebar, then click Real-Time to open the\nReal-Time Performance Panel.\nMonitoring metrics in real-time allows you to respond to time-critical\nissues right away.",
  "headings": [],
  "tokenEstimate": 0,
  "codeExamples": {
    "total": 0,
    "byLanguage": {}
  }
}
